slumbercache
