Metadata-Version: 1.0
Name: slumbercache
Version: 0.1.1
Summary: A library that makes consuming a REST API easier and more convenient with Cache
Home-page: http://github.com/snagajob/slumbercache
Author: Salar Rahmanian
Author-email: opensource@softinio.com
License: UNKNOWN
Platform: UNKNOWN
